bpc_utils/__init__.py
bpc_utils/argparse.py
bpc_utils/context.py
bpc_utils/fileprocessing.py
bpc_utils/logging.py
bpc_utils/misc.py
bpc_utils/multiprocessing.py
bpc_utils/parsing.py
bpc_utils/py.typed
bpc_utils/typing.py
bpc_utils-0.10.1.dist-info/LICENSE
bpc_utils-0.10.1.dist-info/METADATA
bpc_utils-0.10.1.dist-info/WHEEL
bpc_utils-0.10.1.dist-info/top_level.txt
bpc_utils-0.10.1.dist-info/RECORD
