Metadata-Version: 2.1
Name: bpc-utils
Version: 0.10.1
Summary: Utility library for the Python bpc compiler.
Home-page: https://github.com/pybpc/bpc-utils
Author: Saiyang Gou
Author-email: gousaiyang223@gmail.com
License: MIT
Keywords: bpc backport utilities
Platform: UNKNOWN
Classifier: Development Status :: 5 - Production/Stable
Classifier: Intended Audience :: Developers
Classifier: Intended Audience :: Information Technology
Classifier: License :: OSI Approved :: MIT License
Classifier: Operating System :: OS Independent
Classifier: Programming Language :: Python :: 3.4
Classifier: Programming Language :: Python :: 3.5
Classifier: Programming Language :: Python :: 3.6
Classifier: Programming Language :: Python :: 3.7
Classifier: Programming Language :: Python :: 3.8
Classifier: Programming Language :: Python :: 3.9
Classifier: Programming Language :: Python :: 3 :: Only
Classifier: Topic :: Software Development
Classifier: Topic :: Utilities
Classifier: Typing :: Typed
Requires-Python: >=3.4
Requires-Dist: parso (>=0.6.0)
Requires-Dist: typing-extensions
Requires-Dist: typing ; python_version < "3.5"
Provides-Extra: docs
Requires-Dist: Sphinx ; extra == 'docs'
Requires-Dist: sphinx-autodoc-typehints ; extra == 'docs'
Provides-Extra: lint
Requires-Dist: flake8 ; extra == 'lint'
Requires-Dist: pylint ; extra == 'lint'
Requires-Dist: mypy ; extra == 'lint'
Requires-Dist: bandit (>=1.6.3) ; extra == 'lint'
Requires-Dist: vermin (>=1.1.0) ; extra == 'lint'
Requires-Dist: colorlabels (>=0.7.0) ; extra == 'lint'
Requires-Dist: parso (>=0.8.0) ; extra == 'lint'
Provides-Extra: test
Requires-Dist: pytest (>=4.5.0) ; extra == 'test'
Requires-Dist: pytest-doctestplus (>=0.5.0) ; extra == 'test'
Requires-Dist: coverage ; extra == 'test'
